{"coverage": null, "traversable": 0, "revealed": 0, "line-count": 10904, "syntax": {"channel.h": [{"total": 8940, "count": 285, "unique": 76, "minimum-value": 0, "average-value": 31.36842105263158, "maximum-value": 98, "average-frequency": 3.75, "deviation": 27.130892328848255, "distance": 24.031763619575237}, {"total": 6270, "count": 198, "unique": 57, "minimum-value": 0, "average-value": 31.666666666666668, "maximum-value": 98, "average-frequency": 3.473684210526316, "deviation": 30.269329745343278, "distance": 27.86195286195285}, {"total": 2529, "count": 80, "unique": 44, "minimum-value": 1, "average-value": 31.6125, "maximum-value": 68, "average-frequency": 1.8181818181818181, "deviation": 18.182748520232032, "distance": 15.427812499999998}, {"total": 141, "count": 7, "unique": 6, "minimum-value": 7, "average-value": 20.142857142857142, "maximum-value": 42, "average-frequency": 1.1666666666666667, "deviation": 12.0526057814254, "distance": 10.448979591836734}], "port.h": [{"total": 5284, "count": 230, "unique": 68, "minimum-value": 0, "average-value": 22.973913043478262, "maximum-value": 123, "average-frequency": 3.3823529411764706, "deviation": 22.867086987563294, "distance": 17.40279773156901}, {"total": 2033, "count": 121, "unique": 38, "minimum-value": 0, "average-value": 16.801652892561982, "maximum-value": 93, "average-frequency": 3.1842105263157894, "deviation": 23.382418992249352, "distance": 18.031828427020002}, {"total": 2832, "count": 87, "unique": 52, "minimum-value": 5, "average-value": 32.55172413793103, "maximum-value": 123, "average-frequency": 1.6730769230769231, "deviation": 21.63636711846098, "distance": 17.15497423701943}, {"total": 419, "count": 22, "unique": 12, "minimum-value": 13, "average-value": 19.045454545454547, "maximum-value": 34, "average-frequency": 1.8333333333333333, "deviation": 4.547499539979714, "distance": 3.1404958677685952}], "module.c": [{"total": 61216, "count": 3732, "unique": 91, "minimum-value": 0, "average-value": 16.40300107181136, "maximum-value": 115, "average-frequency": 41.010989010989015, "deviation": 18.33095974882297, "distance": 14.632116545987358}, {"total": 8685, "count": 1269, "unique": 60, "minimum-value": 0, "average-value": 6.843971631205674, "maximum-value": 115, "average-frequency": 21.15, "deviation": 13.207297526201554, "distance": 9.273376590714747}, {"total": 27055, "count": 1311, "unique": 85, "minimum-value": 1, "average-value": 20.636918382913805, "maximum-value": 98, "average-frequency": 15.423529411764706, "deviation": 18.83877505508519, "distance": 14.788400211552645}, {"total": 14040, "count": 687, "unique": 73, "minimum-value": 1, "average-value": 20.436681222707424, "maximum-value": 98, "average-frequency": 9.41095890410959, "deviation": 17.78682581808659, "distance": 14.22026022895572}, {"total": 7482, "count": 329, "unique": 64, "minimum-value": 1, "average-value": 22.741641337386017, "maximum-value": 88, "average-frequency": 5.140625, "deviation": 18.520262419910907, "distance": 15.537864579965074}, {"total": 3119, "count": 102, "unique": 45, "minimum-value": 2, "average-value": 30.57843137254902, "maximum-value": 84, "average-frequency": 2.2666666666666666, "deviation": 20.244794186581768, "distance": 17.51441753171858}, {"total": 571, "count": 27, "unique": 14, "minimum-value": 1, "average-value": 21.14814814814815, "maximum-value": 55, "average-frequency": 1.9285714285714286, "deviation": 16.054775921948522, "distance": 14.079561042524006}, {"total": 264, "count": 7, "unique": 7, "minimum-value": 27, "average-value": 37.714285714285715, "maximum-value": 47, "average-frequency": 1.0, "deviation": 6.755194524306794, "distance": 6.040816326530612}], "port.c": [{"total": 14956, "count": 1130, "unique": 75, "minimum-value": 0, "average-value": 13.235398230088496, "maximum-value": 119, "average-frequency": 15.066666666666666, "deviation": 16.628405807793765, "distance": 11.99305818779858}, {"total": 2113, "count": 316, "unique": 39, "minimum-value": 0, "average-value": 6.686708860759493, "maximum-value": 119, "average-frequency": 8.102564102564102, "deviation": 15.16491455538738, "distance": 9.61027880147412}, {"total": 4840, "count": 293, "unique": 54, "minimum-value": 1, "average-value": 16.51877133105802, "maximum-value": 87, "average-frequency": 5.425925925925926, "deviation": 17.268917683059858, "distance": 12.651306363498707}, {"total": 2593, "count": 186, "unique": 41, "minimum-value": 1, "average-value": 13.940860215053764, "maximum-value": 78, "average-frequency": 4.536585365853658, "deviation": 17.21157860190946, "distance": 11.88507341889235}, {"total": 2087, "count": 150, "unique": 34, "minimum-value": 1, "average-value": 13.913333333333334, "maximum-value": 78, "average-frequency": 4.411764705882353, "deviation": 14.645106880987779, "distance": 9.807377777777775}, {"total": 1883, "count": 117, "unique": 27, "minimum-value": 1, "average-value": 16.094017094017094, "maximum-value": 62, "average-frequency": 4.333333333333333, "deviation": 13.968207433514534, "distance": 10.434655562860689}, {"total": 893, "count": 38, "unique": 20, "minimum-value": 1, "average-value": 23.5, "maximum-value": 67, "average-frequency": 1.9, "deviation": 20.147809075090915, "distance": 16.894736842105264}, {"total": 253, "count": 17, "unique": 9, "minimum-value": 6, "average-value": 14.882352941176471, "maximum-value": 41, "average-frequency": 1.8888888888888888, "deviation": 11.493641991482669, "distance": 9.259515570934255}, {"total": 190, "count": 10, "unique": 8, "minimum-value": 6, "average-value": 19.0, "maximum-value": 31, "average-frequency": 1.25, "deviation": 9.16515138991168, "distance": 8.4}, {"total": 27, "count": 1, "unique": 1, "minimum-value": 27, "average-value": 27.0, "maximum-value": 27, "average-frequency": 1.0, "deviation": 0.0, "distance": 0.0}, {"total": 77, "count": 2, "unique": 2, "minimum-value": 31, "average-value": 38.5, "maximum-value": 46, "average-frequency": 1.0, "deviation": 7.5, "distance": 7.5}], "module.h": [{"total": 647, "count": 31, "unique": 23, "minimum-value": 0, "average-value": 20.870967741935484, "maximum-value": 47, "average-frequency": 1.3478260869565217, "deviation": 15.522599415428548, "distance": 13.41519250780437}, {"total": 385, "count": 19, "unique": 14, "minimum-value": 0, "average-value": 20.263157894736842, "maximum-value": 47, "average-frequency": 1.3571428571428572, "deviation": 18.364273396900895, "distance": 17.22437673130194}, {"total": 262, "count": 12, "unique": 11, "minimum-value": 10, "average-value": 21.833333333333332, "maximum-value": 43, "average-frequency": 1.0909090909090908, "deviation": 9.325889889025188, "distance": 7.472222222222221}], "datagram.h": [{"total": 1354, "count": 44, "unique": 28, "minimum-value": 0, "average-value": 30.772727272727273, "maximum-value": 85, "average-frequency": 1.5714285714285714, "deviation": 28.778040583658758, "distance": 26.024793388429757}, {"total": 640, "count": 30, "unique": 17, "minimum-value": 0, "average-value": 21.333333333333332, "maximum-value": 81, "average-frequency": 1.7647058823529411, "deviation": 26.36833117375631, "distance": 23.066666666666663}, {"total": 714, "count": 14, "unique": 14, "minimum-value": 12, "average-value": 51.0, "maximum-value": 85, "average-frequency": 1.0, "deviation": 22.646349437760225, "distance": 19.571428571428573}]}}