["module", [["import", [], {"area": [[4, 1], [4, 36]], "path": ["collections", "abc", "Sequence"], "relative": 0, "factor": true, "identifier": "Sequence"}], ["import", [], {"area": [[6, 1], [8, 15]], "path": ["fault", "context", "tools"], "relative": 0, "factor": true, "identifier": "tools"}], ["class", [["inheritance", [["type", [], {"syntax": "object", "reference": "object", "area": [[9, 15], [9, 20]]}]], {}], ["classmethod", [["parameter", [], {"identifier": "Class", "area": [[35, 19], [35, 24]]}], ["parameter", [], {"identifier": "totals", "area": [[35, 26], [35, 32]]}], ["parameter", [], {"identifier": "counts", "area": [[35, 34], [35, 40]]}], ["parameter", [], {"identifier": "sum", "area": [[35, 42], [35, 45]], "default": "<ast.Name object at 0x102cab610>", "optional": true}]], {"identifier": "from_vectors", "area": [[35, 2], [43, 13]], "documented": [[36, 3], [38, 5]]}], ["classmethod", [["parameter", [], {"identifier": "Class", "area": [[44, 19], [44, 24]]}], ["parameter", [], {"identifier": "subject", "area": [[44, 26], [44, 33]]}], ["parameter", [], {"identifier": "count", "area": [[44, 35], [44, 39]]}]], {"identifier": "from_factors", "area": [[44, 2], [47, 14]], "documented": [[45, 3], [47, 14]]}], ["staticmethod", [["parameter", [], {"identifier": "p", "area": [[48, 16], [48, 16]]}]], {"identifier": "frequency", "area": [[48, 2], [54, 14]], "documented": [[49, 3], [51, 5]]}], ["staticmethod", [["parameter", [], {"identifier": "p", "area": [[55, 12], [55, 12]]}]], {"identifier": "value", "area": [[55, 2], [59, 18]], "documented": [[56, 3], [58, 5]]}], ["method", [["parameter", [], {"identifier": "self", "area": [[61, 15], [61, 18]]}]], {"identifier": "__repr__", "area": [[61, 2], [70, 10]], "documented": [[62, 3], [70, 10]]}], ["property", [], {"identifier": "remainder", "area": [[71, 2], [78, 10]], "documented": [[72, 3], [75, 5]]}], ["property", [], {"identifier": "rational", "area": [[79, 2], [83, 53]], "documented": [[80, 3], [82, 5]]}], ["method", [["parameter", [], {"identifier": "self", "area": [[85, 10], [85, 14]]}], ["parameter", [], {"identifier": "values", "area": [[85, 16], [85, 21]]}]], {"identifier": "add", "area": [[85, 2], [101, 37]], "documented": [[86, 3], [90, 5]]}], ["method", [["parameter", [], {"identifier": "self", "area": [[103, 13], [103, 17]]}], ["parameter", [], {"identifier": "delta", "area": [[103, 19], [103, 23]]}]], {"identifier": "adjust", "area": [[103, 2], [112, 3]], "documented": [[104, 3], [107, 5]]}], ["method", [["parameter", [], {"identifier": "self", "area": [[114, 14], [114, 17]]}]], {"identifier": "__int__", "area": [[114, 2], [117, 15]], "documented": [[115, 3], [117, 15]]}]], {"identifier": "Product", "area": [[9, 1], [117, 15]], "documented": [[10, 2], [29, 4]]}], ["class", [["inheritance", [["type", [], {"syntax": "object", "reference": "object", "area": [[118, 15], [118, 20]]}]], {}], ["property", [], {"identifier": "minimum", "area": [[133, 2], [139, 10]], "documented": [[134, 3], [136, 5]]}], ["property", [], {"identifier": "maximum", "area": [[140, 2], [146, 10]], "documented": [[141, 3], [143, 5]]}], ["property", [], {"identifier": "span", "area": [[147, 2], [151, 55]], "documented": [[148, 3], [150, 5]]}], ["method", [["parameter", [], {"identifier": "self", "area": [[153, 11], [153, 14]]}]], {"identifier": "imin", "area": [[153, 2], [157, 40]], "documented": [[154, 3], [156, 5]]}], ["method", [["parameter", [], {"identifier": "self", "area": [[159, 11], [159, 14]]}]], {"identifier": "imax", "area": [[159, 2], [165, 15]], "documented": [[160, 3], [162, 5]]}]], {"identifier": "Profile", "area": [[118, 1], [165, 15]], "documented": [[119, 2], [127, 4]]}], ["class", [["inheritance", [["type", [], {"syntax": "object", "reference": "object", "area": [[166, 18], [166, 23]]}]], {}], ["property", [["type", [], {"syntax": "Product", "reference": "Product", "area": [[197, 20], [197, 26]]}]], {"identifier": "mean", "area": [[197, 2], [204, 52]], "documented": [[198, 3], [201, 5]]}], ["method", [["parameter", [], {"identifier": "self", "area": [[206, 15], [206, 18]]}]], {"identifier": "profiles", "area": [[206, 2], [209, 37]], "documented": [[207, 3], [207, 39]]}], ["method", [["parameter", [], {"identifier": "self", "area": [[211, 14], [211, 17]]}]], {"identifier": "__str__", "area": [[211, 2], [223, 5]], "documented": [[212, 3], [212, 20]]}], ["method", [["parameter", [], {"identifier": "self", "area": [[225, 14], [225, 18]]}], ["parameter", [], {"identifier": "deviation", "area": [[225, 20], [225, 29]], "default": "<ast.Constant object at 0x102c8e550>", "optional": true}]], {"identifier": "summary", "area": [[225, 2], [242, 3]], "documented": [[226, 3], [226, 16]]}]], {"identifier": "Statistics", "area": [[166, 1], [242, 3]], "documented": [[167, 2], [188, 4]]}]], {"identifier": "/x/p/integration/system/metrics/types.py", "area": [[1, 1], [241, 4]], "documented": [[1, 1], [3, 3]], "source-encoding": "utf-8"}]